{
  "version": 3.1,
  "configRevision": 1,
  "nuker_blocks": [],
  "xray_blocks": [
    "gold_ore",
    "iron_ore",
    "coal_ore",
    "redstone_ore",
    "emerald_ore",
    "diamond_ore",
    "lapis_ore",
    "lapis_block",
    "gold_block",
    "iron_block",
    "diamond_block",
    "emerald_block",
    "obsidian",
    "spawner",
    "end_portal_frame"
  ],
  "ghosthand_blocks": [],
  "esp_blocks": [],
  "auto_eject_items_new": [],
  "properties": {
    "keybind": -1,
    "state": false,
    "pinned": false
  },
  "autoeat": {
    "keybind": -1,
    "state": false,
    "pinned": false
  },
  "autoeject": {
    "keybind": -1,
    "state": false,
    "pinned": false
  },
  "autofish": {
    "keybind": -1,
    "state": false,
    "pinned": false
  },
  "automine": {
    "keybind": -1,
    "state": false,
    "pinned": false
  },
  "autoparkour": {
    "keybind": -1,
    "state": false,
    "pinned": false
  },
  "autoreconnect": {
    "keybind": -1,
    "state": false,
    "pinned": false,
    "reconnect_delay": 5.0
  },
  "autosneak": {
    "keybind": -1,
    "state": false,
    "pinned": false
  },
  "autosprint": {
    "keybind": -1,
    "state": false,
    "pinned": false
  },
  "autosteal": {
    "keybind": -1,
    "state": false,
    "pinned": false
  },
  "autotool": {
    "keybind": -1,
    "state": false,
    "pinned": false
  },
  "autototem": {
    "keybind": -1,
    "state": false,
    "pinned": false
  },
  "autowalk": {
    "keybind": -1,
    "state": false,
    "pinned": false
  },
  "autosign": {
    "keybind": -1,
    "state": false,
    "pinned": false
  },
  "autopot": {
    "keybind": -1,
    "state": false,
    "pinned": false
  },
  "autosoup": {
    "keybind": -1,
    "state": false,
    "pinned": false
  },
  "combatsettings": {
    "keybind": -1,
    "state": false,
    "pinned": false
  },
  "criticals": {
    "keybind": 84,
    "state": true,
    "pinned": false
  },
  "antiknockback": {
    "keybind": -1,
    "state": true,
    "pinned": false
  },
  "autoarmor": {
    "keybind": -1,
    "state": false,
    "pinned": true
  },
  "autodisconnect": {
    "keybind": -1,
    "state": false,
    "pinned": false
  },
  "autorespawn": {
    "keybind": -1,
    "state": false,
    "pinned": false
  },
  "bowaimbot": {
    "keybind": 82,
    "state": true,
    "pinned": false,
    "range": 100.0
  },
  "killaura": {
    "keybind": 82,
    "state": true,
    "pinned": false
  },
  "reach": {
    "keybind": 88,
    "state": true,
    "pinned": false,
    "reach": 5.0
  },
  "regen": {
    "keybind": -1,
    "state": false,
    "pinned": false
  },
  "triggerbot": {
    "keybind": -1,
    "state": false,
    "pinned": false
  },
  "autoclicker": {
    "keybind": -1,
    "state": false,
    "pinned": false,
    "cps": 17,
    "right_click": false
  },
  "activemods": {
    "keybind": -1,
    "state": true,
    "pinned": true,
    "rgb_mode": true
  },
  "bettercrosshair": {
    "keybind": -1,
    "state": false,
    "pinned": false
  },
  "gui": {
    "keybind": 344,
    "state": false,
    "pinned": false,
    "tooltips": true,
    "rgb_mode": true,
    "rgb_speed": 0.006,
    "rgb_toggles": false,
    "red": 100.0,
    "green": 190.0,
    "blue": 210.0
  },
  "hud": {
    "keybind": -1,
    "state": true,
    "pinned": true
  },
  "tabgui": {
    "keybind": 70,
    "state": true,
    "pinned": true,
    "rgb": true
  },
  "radar": {
    "keybind": -1,
    "state": false,
    "pinned": false
  },
  "miniplayer": {
    "keybind": -1,
    "state": false,
    "pinned": false
  },
  "antislowdown": {
    "keybind": 67,
    "state": false,
    "pinned": false,
    "sneaking": true,
    "eating": true,
    "webs": true,
    "blocks": true,
    "hunger": true
  },
  "bhop": {
    "keybind": -1,
    "state": false,
    "pinned": false
  },
  "blink": {
    "keybind": -1,
    "state": false,
    "pinned": false
  },
  "bunnyjump": {
    "keybind": -1,
    "state": false,
    "pinned": false,
    "height": 8.0
  },
  "elytraflight": {
    "keybind": -1,
    "state": false,
    "pinned": false
  },
  "fastladders": {
    "keybind": -1,
    "state": false,
    "pinned": false
  },
  "flight": {
    "keybind": 70,
    "state": false,
    "pinned": false,
    "flight_speed": 1.0,
    "boat_fly": false,
    "horse_fly": false,
    "damage_mode": false
  },
  "freecam": {
    "keybind": -1,
    "state": false,
    "pinned": false
  },
  "glide": {
    "keybind": -1,
    "state": false,
    "pinned": false
  },
  "inventorywalk": {
    "keybind": -1,
    "state": false,
    "pinned": false
  },
  "jesus": {
    "keybind": -1,
    "state": false,
    "pinned": false
  },
  "nofall": {
    "keybind": -1,
    "state": false,
    "pinned": false
  },
  "airjump": {
    "keybind": -1,
    "state": false,
    "pinned": false
  },
  "safewalk": {
    "keybind": 90,
    "state": true,
    "pinned": false
  },
  "scaffoldwalk": {
    "keybind": 81,
    "state": false,
    "pinned": false
  },
  "speed": {
    "keybind": -1,
    "state": false,
    "pinned": false
  },
  "spider": {
    "keybind": -1,
    "state": false,
    "pinned": false
  },
  "step": {
    "keybind": -1,
    "state": false,
    "pinned": false
  },
  "waterjump": {
    "keybind": -1,
    "state": false,
    "pinned": false
  },
  "jetpack": {
    "keybind": -1,
    "state": false,
    "pinned": false
  },
  "horsejump": {
    "keybind": -1,
    "state": false,
    "pinned": false
  },
  "antiafk": {
    "keybind": -1,
    "state": false,
    "pinned": false
  },
  "annoy": {
    "keybind": -1,
    "state": false,
    "pinned": false
  },
  "chatcolor": {
    "keybind": -1,
    "state": false,
    "pinned": false
  },
  "chatmute": {
    "keybind": -1,
    "state": false,
    "pinned": false
  },
  "chatspammer": {
    "keybind": -1,
    "state": false,
    "pinned": false
  },
  "derp": {
    "keybind": -1,
    "state": false,
    "pinned": false
  },
  "fancychat": {
    "keybind": -1,
    "state": false,
    "pinned": false
  },
  "ghosthand": {
    "keybind": -1,
    "state": false,
    "pinned": false
  },
  "irc-mute": {
    "keybind": -1,
    "state": false,
    "pinned": false
  },
  "nameprotect": {
    "keybind": -1,
    "state": false,
    "pinned": false
  },
  "oneclickfriends": {
    "keybind": -1,
    "state": false,
    "pinned": false
  },
  "skinblinker": {
    "keybind": -1,
    "state": false,
    "pinned": false
  },
  "twerk": {
    "keybind": -1,
    "state": false,
    "pinned": false,
    "delay": 1.0
  },
  "unfocusedcpu": {
    "keybind": -1,
    "state": true,
    "pinned": false,
    "limited_fps": 5
  },
  "shulkerpeek": {
    "keybind": -1,
    "state": false,
    "pinned": false
  },
  "inventory++": {
    "keybind": -1,
    "state": false,
    "pinned": false
  },
  "antianimation": {
    "keybind": -1,
    "state": false,
    "pinned": false,
    "totem": true
  },
  "antiblind": {
    "keybind": -1,
    "state": false,
    "pinned": false
  },
  "betternametags": {
    "keybind": -1,
    "state": false,
    "pinned": false
  },
  "breadcrumbs": {
    "keybind": -1,
    "state": false,
    "pinned": false
  },
  "esp": {
    "keybind": 77,
    "state": false,
    "pinned": false,
    "chests/barrels": true,
    "players": true,
    "mobs/animals": true,
    "items": true
  },
  "fullbright": {
    "keybind": -1,
    "state": false,
    "pinned": false,
    "max_brightness": 16.0
  },
  "noweather": {
    "keybind": -1,
    "state": false,
    "pinned": false
  },
  "tracers": {
    "keybind": -1,
    "state": false,
    "pinned": false
  },
  "trajectories": {
    "keybind": -1,
    "state": false,
    "pinned": false
  },
  "truesight": {
    "keybind": -1,
    "state": false,
    "pinned": false
  },
  "waypoints": {
    "keybind": -1,
    "state": false,
    "pinned": false,
    "death_waypoints": false
  },
  "xray": {
    "keybind": -1,
    "state": false,
    "pinned": false
  },
  "rainbowenchant": {
    "keybind": -1,
    "state": false,
    "pinned": false
  },
  "blockesp": {
    "keybind": -1,
    "state": false,
    "pinned": false
  },
  "dinnerbone": {
    "keybind": -1,
    "state": false,
    "pinned": false
  },
  "barriervision": {
    "keybind": -1,
    "state": false,
    "pinned": false
  },
  "fastbreak": {
    "keybind": -1,
    "state": false,
    "pinned": false,
    "speed": 2.0
  },
  "fastplace": {
    "keybind": -1,
    "state": false,
    "pinned": false
  },
  "nuker": {
    "keybind": -1,
    "state": false,
    "pinned": false
  },
  "timer": {
    "keybind": -1,
    "state": false,
    "pinned": false
  },
  "anticactus": {
    "keybind": -1,
    "state": false,
    "pinned": false
  },
  "antiberrybush": {
    "keybind": -1,
    "state": false,
    "pinned": false
  },
  "murdermysteries": {
    "keybind": -1,
    "state": false,
    "pinned": false
  },
  "prophunt": {
    "keybind": -1,
    "state": false,
    "pinned": false,
    "tracers": true,
    "outline": true
  },
  "friends": [],
  "waypoints_array": [],
  "macros": [],
  "user_ignore_list": [],
  "first_time_setup_": true,
  "Dhas_shown_welcome_screen_DLL": true,
  "irc_rules": true,
  "using_mod_gui": true,
  "World_x": 530,
  "World_y": 110,
  "World_hidden": true,
  "Minigames_x": 530,
  "Minigames_y": 170,
  "Minigames_hidden": true,
  "Dhas_shown_welcome_screen_D_update_TPP": true,
  "current_aristois_version": 247,
  "Movement_x": 290,
  "Movement_y": 50,
  "Movement_hidden": true,
  "Auto_x": 290,
  "Auto_y": 170,
  "Auto_hidden": true,
  "Other_x": 290,
  "Other_y": 110,
  "Other_hidden": true,
  "Combat_x": 50,
  "Combat_y": 110,
  "Combat_hidden": true,
  "Pinned_hidden": false,
  "Render_x": 50,
  "Render_y": 170,
  "Render_hidden": true,
  "Pinned_x": 50,
  "Pinned_y": 50
}
